fbtree/__init__.py
fbtree/analysis/__init__.py
fbtree/analysis/path_analysis.py
fbtree/core/__init__.py
fbtree/core/fiber.py
fbtree/core/move.py
fbtree/core/tree.py
fbtree/storage/__init__.py
fbtree/storage/base.py
fbtree/storage/memory.py
fbtree/storage/sqlite.py
fbtree/utils/__init__.py
fbtree/utils/cache.py
fbtree/utils/serialization.py
fbtree/visualization/__init__.py
fbtree/visualization/graph_viz.py
fbtree/visualization/text_viz.py
fbtree-1.2.0.dist-info/LICENSE
fbtree-1.2.0.dist-info/METADATA
fbtree-1.2.0.dist-info/WHEEL
fbtree-1.2.0.dist-info/top_level.txt
fbtree-1.2.0.dist-info/RECORD
