Metadata-Version: 2.2
Name: fbtree
Version: 1.2.0
Summary: A path-oriented database for storing and analyzing sequential decision paths
Home-page: https://github.com/Karesis/Fbtree
Author: 杨亦锋 (Karesis)
Author-email: "杨亦锋 (Karesis)" <yangyifeng23@mails.ucas.ac.cn>
License: MIT
Project-URL: Homepage, https://github.com/Karesis/Fbtree
Project-URL: Documentation, https://github.com/Karesis/Fbtree#readme
Project-URL: Repository, https://github.com/Karesis/Fbtree.git
Project-URL: Issues, https://github.com/Karesis/Fbtree/issues
Keywords: decision-tree,database,sequential-data,path-analysis,decision-making
Classifier: Development Status :: 4 - Beta
Classifier: Intended Audience :: Developers
Classifier: Intended Audience :: Science/Research
Classifier: License :: OSI Approved :: MIT License
Classifier: Programming Language :: Python :: 3
Classifier: Programming Language :: Python :: 3.7
Classifier: Programming Language :: Python :: 3.8
Classifier: Programming Language :: Python :: 3.9
Classifier: Programming Language :: Python :: 3.10
Classifier: Topic :: Database
Classifier: Topic :: Scientific/Engineering :: Artificial Intelligence
Classifier: Topic :: Software Development :: Libraries
Requires-Python: >=3.6
License-File: LICENSE
Provides-Extra: dev
Requires-Dist: pytest>=6.0; extra == "dev"
Requires-Dist: black; extra == "dev"
Requires-Dist: flake8; extra == "dev"
Requires-Dist: mypy; extra == "dev"
Requires-Dist: isort; extra == "dev"
Provides-Extra: docs
Requires-Dist: sphinx; extra == "docs"
Requires-Dist: sphinx-rtd-theme; extra == "docs"
Dynamic: author
Dynamic: home-page
Dynamic: requires-python
